awsservice/__init__.py
awsservice/cloudwatch_service.py
awsservice/ec2_service.py
awsservice/s3_service.py
awsservice-0.0.7.dist-info/LICENSE
awsservice-0.0.7.dist-info/METADATA
awsservice-0.0.7.dist-info/WHEEL
awsservice-0.0.7.dist-info/top_level.txt
awsservice-0.0.7.dist-info/RECORD
