Metadata-Version: 2.1
Name: awsservice
Version: 0.0.7
Summary: A small example package for AWS: S3, EC2, CloudWatch
Home-page: https://github.com/Vitalikys/AWS_s3_app
Author: Vitalik Kost
Author-email: vitalii.kostyreva@gmail.com
License: UNKNOWN
Platform: UNKNOWN
Classifier: Programming Language :: Python :: 3
Classifier: License :: OSI Approved :: MIT License
Classifier: Operating System :: OS Independent
Requires-Python: >=3.8
License-File: LICENSE
Requires-Dist: boto3
Requires-Dist: pytz
Requires-Dist: botocore
